yxmap/__init__.py
yxmap/config.py
yxmap/map.py
yxmap/plot.py
yxmap/raster.py
yxmap/shape.py
yxmap/versions.py
yxmap/data/gallery.ipynb
yxmap/data/natural_earth/ne_10m_admin_0_countries/.DS_Store
yxmap/data/natural_earth/ne_10m_admin_0_countries/ne_10m_admin_0_countries.README.html
yxmap/data/natural_earth/ne_10m_admin_0_countries/ne_10m_admin_0_countries.VERSION.txt
yxmap/data/natural_earth/ne_10m_admin_0_countries/ne_10m_admin_0_countries.changes_log.csv
yxmap/data/natural_earth/ne_10m_admin_0_countries/ne_10m_admin_0_countries.changes_log.csv.md
yxmap/data/natural_earth/ne_10m_admin_0_countries/ne_10m_admin_0_countries.cpg
yxmap/data/natural_earth/ne_10m_admin_0_countries/ne_10m_admin_0_countries.dbf
yxmap/data/natural_earth/ne_10m_admin_0_countries/ne_10m_admin_0_countries.new_names.csv
yxmap/data/natural_earth/ne_10m_admin_0_countries/ne_10m_admin_0_countries.prj
yxmap/data/natural_earth/ne_10m_admin_0_countries/ne_10m_admin_0_countries.shp
yxmap/data/natural_earth/ne_10m_admin_0_countries/ne_10m_admin_0_countries.shp.changes_log.csv
yxmap/data/natural_earth/ne_10m_admin_0_countries/ne_10m_admin_0_countries.shp.changes_log.csv.md
yxmap/data/natural_earth/ne_10m_admin_0_countries/ne_10m_admin_0_countries.shp.new_names.csv
yxmap/data/natural_earth/ne_10m_admin_0_countries/ne_10m_admin_0_countries.shp.summary_log.csv
yxmap/data/natural_earth/ne_10m_admin_0_countries/ne_10m_admin_0_countries.shp.summary_log.csv.md
yxmap/data/natural_earth/ne_10m_admin_0_countries/ne_10m_admin_0_countries.shx
yxmap/data/natural_earth/ne_10m_admin_0_countries/ne_10m_admin_0_countries.summary_log.csv
yxmap/data/natural_earth/ne_10m_admin_0_countries/ne_10m_admin_0_countries.summary_log.csv.md
yxmap-0.0.1.dist-info/LICENSE
yxmap-0.0.1.dist-info/METADATA
yxmap-0.0.1.dist-info/WHEEL
yxmap-0.0.1.dist-info/top_level.txt
yxmap-0.0.1.dist-info/RECORD
