Metadata-Version: 2.1
Name: yxmap
Version: 0.0.1
Summary: Xu Yuxing's personal geographic data-processing tools
Home-page: https://github.com/SouthernCD/yxmap
Author: Yuxing Xu
Author-email: xuyuxing@mail.kib.ac.cn
Requires-Python: >=3.5
License-File: LICENSE
Requires-Dist: numpy
Requires-Dist: pandas
Requires-Dist: matplotlib
Requires-Dist: geopandas >=0.14.3
Requires-Dist: statsmodels >=0.14.1
Requires-Dist: rasterio >=1.3.10
